README.md
setup.py
greasepaint/__init__.py
greasepaint/_version.py
greasepaint/landmarks.py
greasepaint/presets.py
greasepaint/shadowing.py
greasepaint/utils.py
greasepaint.egg-info/PKG-INFO
greasepaint.egg-info/SOURCES.txt
greasepaint.egg-info/dependency_links.txt
greasepaint.egg-info/requires.txt
greasepaint.egg-info/top_level.txt