Metadata-Version: 1.1
Name: greasepaint
Version: 0.0.1
Summary: A python library to manipulate the faces. Think snapchat but weirder.
Home-page: https://github.com/thoppe/greasepaint
Author: Travis Hoppe
Author-email: travis.hoppe+greasepaint@gmail.com
License: CC-SA
Keywords: art
Platform: UNKNOWN
Classifier: Development Status :: 3 - Alpha
Classifier: Intended Audience :: Developers
Classifier: License :: OSI Approved :: MIT License
Classifier: Programming Language :: Python :: 3.6
